salty/__init__.py
salty/datatype.py
salty/tools.py
saltype/__init__.py
saltype/datatype.py
saltype/tools.py
saltype-1.4.dist-info/LICENSE
saltype-1.4.dist-info/METADATA
saltype-1.4.dist-info/WHEEL
saltype-1.4.dist-info/top_level.txt
saltype-1.4.dist-info/RECORD
