Metadata-Version: 2.1
Name: saltype
Version: 1.4
Summary: Symbolic algebra light type
Home-page: https://github.com/VolkerSiep/saltype
Author: Volker Siepmann
Author-email: volker.siepmann@gmail.com,
Keywords: symbolic algebra
Classifier: License :: OSI Approved :: GNU Lesser General Public License v3 or later (LGPLv3+)
Classifier: Programming Language :: Python :: 3
Classifier: Topic :: Scientific/Engineering
Requires-Python: >=3.9
License-File: LICENSE
Requires-Dist: numpy
Provides-Extra: dev
Requires-Dist: Sphinx ; extra == 'dev'
Requires-Dist: pytest ; extra == 'dev'
